Metadata-Version: 2.1
Name: random-quote-generator-py
Version: 0.1.3
Summary: Random quate generator
Home-page: https://random-quote-generator-py.readthedocs.io/en/latest/
License: MIT
Author: Manuel Pita
Author-email: mpita1984@gmail.com
Requires-Python: >=3.9,<4.0
Classifier: License :: OSI Approved :: MIT License
Classifier: Programming Language :: Python :: 3
Classifier: Programming Language :: Python :: 3.10
Classifier: Programming Language :: Python :: 3.9
Project-URL: Documentation, https://random-quote-generator-py.readthedocs.io/en/latest/?badge=latest
Project-URL: Repository, https://github.com/mpita/random-quote-generator
